trivy_streamlit/__init__.py
trivy_streamlit/main_module.py
trivy_streamlit-0.7.dist-info/LICENSE
trivy_streamlit-0.7.dist-info/METADATA
trivy_streamlit-0.7.dist-info/WHEEL
trivy_streamlit-0.7.dist-info/entry_points.txt
trivy_streamlit-0.7.dist-info/top_level.txt
trivy_streamlit-0.7.dist-info/RECORD
