Metadata-Version: 2.1
Name: trivy-streamlit
Version: 0.7
Summary: A simple streamlit app for trivy security scanner JSON output
Home-page: https://github.com/mfreeman451/trivy-streamlit
Author: Michael Freeman
Author-email: mfreeman451@gmail.com
License: Apache-2.0
Classifier: Programming Language :: Python :: 3
Classifier: License :: OSI Approved :: Apache Software License
Classifier: Operating System :: OS Independent
Classifier: Topic :: Security
License-File: LICENSE
Requires-Dist: streamlit
